nultack/__init__.py
nultack/core.py
nultack/decode.py
nultack/encode.py
nultack/execute.py
nultack/protection.py
nultack/utils.py
nultack-1.8.1.dist-info/METADATA
nultack-1.8.1.dist-info/WHEEL
nultack-1.8.1.dist-info/top_level.txt
nultack-1.8.1.dist-info/RECORD
